cst_python/__init__.py
cst_python/core/__init__.py
cst_python/core/entities/__init__.py
cst_python/core/entities/coalition.py
cst_python/core/entities/code_rack.py
cst_python/core/entities/codelet.py
cst_python/core/entities/codelet_container.py
cst_python/core/entities/memory.py
cst_python/core/entities/memory_buffer.py
cst_python/core/entities/memory_container.py
cst_python/core/entities/memory_object.py
cst_python/core/entities/memory_observer.py
cst_python/core/entities/mind.py
cst_python/core/entities/raw_memory.py
cst_python/core/entities/rest_memory_container.py
cst_python/core/entities/rest_memory_object.py
cst_python/memory_storage/__init__.py
cst_python/memory_storage/logical_time.py
cst_python/memory_storage/memory_encoder.py
cst_python/memory_storage/memory_storage.py
cst_python/python/__init__.py
cst_python/python/alias.py
cst_python/python/gym/__init__.py
cst_python/python/gym/gym_codelet.py
cst_python-0.3.0.dist-info/LICENSE
cst_python-0.3.0.dist-info/METADATA
cst_python-0.3.0.dist-info/WHEEL
cst_python-0.3.0.dist-info/top_level.txt
cst_python-0.3.0.dist-info/RECORD
