Metadata-Version: 2.1
Name: cst_python
Version: 0.3.0
Summary: Python module of the CST, the Cognitive Systems Toolkit, a toolkit for the construction of cognitive systems and cognitive architectures.
Author-email: "H.IAAC" <hiaac@unicamp.br>
Project-URL: Homepage, https://hiaac.unicamp.br
Project-URL: Bug Tracker, https://github.com/H-IAAC/CST-Python/issues
Classifier: Programming Language :: Python :: 3
Classifier: Operating System :: OS Independent
Classifier: Topic :: Scientific/Engineering
Classifier: Topic :: Scientific/Engineering :: Artificial Intelligence
Classifier: Intended Audience :: Science/Research
Classifier: License :: OSI Approved :: GNU Lesser General Public License v3 (LGPLv3)
Requires-Python: >=3.10
License-File: LICENSE
Provides-Extra: tests
Requires-Dist: mypy; extra == "tests"
Requires-Dist: testbook; extra == "tests"
Requires-Dist: ipython; extra == "tests"
Requires-Dist: ipykernel; extra == "tests"
Requires-Dist: numpy; extra == "tests"
Requires-Dist: matplotlib; extra == "tests"
Requires-Dist: types-redis; extra == "tests"
Provides-Extra: doc-generation
Requires-Dist: sphinx; extra == "doc-generation"
Requires-Dist: sphinx_rtd_theme; extra == "doc-generation"
Requires-Dist: nbsphinx; extra == "doc-generation"
Requires-Dist: sphinx-mdinclude==0.5.4; extra == "doc-generation"
Provides-Extra: dev
Requires-Dist: cffconvert; extra == "dev"
Provides-Extra: gym
Requires-Dist: gymnasium; extra == "gym"
Provides-Extra: memory-storage
Requires-Dist: redis; extra == "memory-storage"
